safety_gymnasium/__init__.py
safety_gymnasium/builder.py
safety_gymnasium/version.py
safety_gymnasium/world.py
safety_gymnasium/agents/__init__.py
safety_gymnasium/agents/ant.py
safety_gymnasium/agents/car.py
safety_gymnasium/agents/doggo.py
safety_gymnasium/agents/point.py
safety_gymnasium/agents/racecar.py
safety_gymnasium/assets/__init__.py
safety_gymnasium/assets/color.py
safety_gymnasium/assets/group.py
safety_gymnasium/assets/robot.py
safety_gymnasium/assets/free_geoms/__init__.py
safety_gymnasium/assets/free_geoms/push_box.py
safety_gymnasium/assets/free_geoms/vases.py
safety_gymnasium/assets/geoms/__init__.py
safety_gymnasium/assets/geoms/apples.py
safety_gymnasium/assets/geoms/buttons.py
safety_gymnasium/assets/geoms/circle.py
safety_gymnasium/assets/geoms/goal.py
safety_gymnasium/assets/geoms/hazards.py
safety_gymnasium/assets/geoms/oranges.py
safety_gymnasium/assets/geoms/pillars.py
safety_gymnasium/assets/geoms/sigwalls.py
safety_gymnasium/assets/geoms/staged_goal.py
safety_gymnasium/assets/geoms/walls.py
safety_gymnasium/assets/meshes/bamboo_wall.obj
safety_gymnasium/assets/meshes/bush.obj
safety_gymnasium/assets/meshes/button.obj
safety_gymnasium/assets/meshes/chassis_differential.STL
safety_gymnasium/assets/meshes/cliff1.obj
safety_gymnasium/assets/meshes/cliff2.obj
safety_gymnasium/assets/meshes/cliff3.obj
safety_gymnasium/assets/meshes/diff_carrier.stl
safety_gymnasium/assets/meshes/diff_ring.stl
safety_gymnasium/assets/meshes/diff_side.stl
safety_gymnasium/assets/meshes/diff_spider.stl
safety_gymnasium/assets/meshes/flower_bush.obj
safety_gymnasium/assets/meshes/goal.obj
safety_gymnasium/assets/meshes/gremlin.obj
safety_gymnasium/assets/meshes/hazard.obj
safety_gymnasium/assets/meshes/left_front_wheel.obj
safety_gymnasium/assets/meshes/left_rear_wheel.obj
safety_gymnasium/assets/meshes/left_steering_hinge.STL
safety_gymnasium/assets/meshes/pillar.obj
safety_gymnasium/assets/meshes/push_box.obj
safety_gymnasium/assets/meshes/racing_track.obj
safety_gymnasium-1.2.0.dist-info/LICENSE
safety_gymnasium-1.2.0.dist-info/METADATA
safety_gymnasium-1.2.0.dist-info/WHEEL
safety_gymnasium-1.2.0.dist-info/top_level.txt
safety_gymnasium-1.2.0.dist-info/RECORD
