Metadata-Version: 2.1
Name: safety-gymnasium
Version: 1.2.0
Summary: A highly scalable and customizable safe reinforcement learning environment.
Author: Safety-Gymnasium Contributors
License: Apache License, Version 2.0
Project-URL: Homepage, https://github.com/PKU-Alignment/safety-gymnasium
Project-URL: Repository, https://github.com/PKU-Alignment/safety-gymnasium
Project-URL: Documentation, https://www.safety-gymnasium.com
Project-URL: Bug Report, https://github.com/PKU-Alignment/safety-gymnasium/issues
Keywords: Safe Reinforcement Learning,RL Environment,MuJoCo
Classifier: Development Status :: 4 - Beta
Classifier: License :: OSI Approved :: Apache Software License
Classifier: Programming Language :: Python :: 3
Classifier: Programming Language :: Python :: 3.8
Classifier: Programming Language :: Python :: 3.9
Classifier: Programming Language :: Python :: 3.10
Classifier: Programming Language :: Python :: 3.11
Classifier: Intended Audience :: Science/Research
Classifier: Topic :: Scientific/Engineering :: Artificial Intelligence
Classifier: Topic :: Software Development :: Libraries :: Python Modules
Requires-Python: >=3.8
License-File: LICENSE
Requires-Dist: gymnasium ==0.28.1
Requires-Dist: gymnasium-robotics ==1.2.2
Requires-Dist: pygame ==2.1.0
Requires-Dist: mujoco ==2.3.3
Requires-Dist: xmltodict >=0.13.0
Requires-Dist: pyyaml >=6.0
Requires-Dist: imageio >=2.27.0
Provides-Extra: lint
Requires-Dist: isort >=5.11.0 ; extra == 'lint'
Requires-Dist: black >=23.1.0 ; extra == 'lint'
Requires-Dist: pylint[spelling] >=2.15.0 ; extra == 'lint'
Requires-Dist: mypy >=0.990 ; extra == 'lint'
Requires-Dist: flake8 ; extra == 'lint'
Requires-Dist: flake8-bugbear ; extra == 'lint'
Requires-Dist: flake8-comprehensions ; extra == 'lint'
Requires-Dist: flake8-docstrings ; extra == 'lint'
Requires-Dist: flake8-pyi ; extra == 'lint'
Requires-Dist: flake8-simplify ; extra == 'lint'
Requires-Dist: doc8 ; extra == 'lint'
Requires-Dist: pydocstyle ; extra == 'lint'
Requires-Dist: pyenchant ; extra == 'lint'
Requires-Dist: pre-commit ; extra == 'lint'
Requires-Dist: myst-parser ; extra == 'lint'
Provides-Extra: test
Requires-Dist: pytest ; extra == 'test'
Requires-Dist: pytest-cov ; extra == 'test'
Requires-Dist: pytest-xdist ; extra == 'test'
